pyqrcode/__init__.py
pyqrcode/builder.py
pyqrcode/tables.py
pyqrcode_binary-1.2.1.dist-info/METADATA
pyqrcode_binary-1.2.1.dist-info/WHEEL
pyqrcode_binary-1.2.1.dist-info/top_level.txt
pyqrcode_binary-1.2.1.dist-info/RECORD
