Metadata-Version: 2.4
Name: pyqrcode-binary
Version: 1.2.1
Summary: A QR code generator written purely in Python with SVG, EPS, PNG and terminal output.
Home-page: https://github.com/di/pyqrcode-binary/
Author: Michael Nooner
Author-email: mnooner256@gmail.com
License: BSD
Keywords: qrcode,qr
Classifier: Development Status :: 4 - Beta
Classifier: Environment :: Console
Classifier: Intended Audience :: Developers
Classifier: License :: OSI Approved :: BSD License
Classifier: Topic :: Software Development :: Libraries :: Python Modules
Classifier: Natural Language :: English
Classifier: Operating System :: OS Independent
Classifier: Operating System :: POSIX
Classifier: Operating System :: Microsoft :: Windows
Classifier: Programming Language :: Python :: 3
Classifier: Programming Language :: Python :: 2.6
Classifier: Programming Language :: Python :: 2.7
Provides-Extra: png
Requires-Dist: pypng>=0.0.13; extra == "png"
Dynamic: author
Dynamic: author-email
Dynamic: classifier
Dynamic: home-page
Dynamic: keywords
Dynamic: license
Dynamic: provides-extra
Dynamic: summary
